stream_chat/__init__.py
stream_chat/__pkg__.py
stream_chat/campaign.py
stream_chat/channel.py
stream_chat/channel_batch_updater.py
stream_chat/client.py
stream_chat/py.typed
stream_chat/query_threads.py
stream_chat/segment.py
stream_chat/async_chat/__init__.py
stream_chat/async_chat/campaign.py
stream_chat/async_chat/channel.py
stream_chat/async_chat/channel_batch_updater.py
stream_chat/async_chat/client.py
stream_chat/async_chat/segment.py
stream_chat/base/__init__.py
stream_chat/base/campaign.py
stream_chat/base/channel.py
stream_chat/base/client.py
stream_chat/base/exceptions.py
stream_chat/base/query_threads.py
stream_chat/base/segment.py
stream_chat/types/__init__.py
stream_chat/types/base.py
stream_chat/types/campaign.py
stream_chat/types/channel_batch.py
stream_chat/types/delivery_receipts.py
stream_chat/types/draft.py
stream_chat/types/rate_limit.py
stream_chat/types/segment.py
stream_chat/types/shared_locations.py
stream_chat/types/stream_response.py
stream_chat-4.29.0.dist-info/licenses/LICENSE
stream_chat-4.29.0.dist-info/METADATA
stream_chat-4.29.0.dist-info/WHEEL
stream_chat-4.29.0.dist-info/top_level.txt
stream_chat-4.29.0.dist-info/RECORD
