Metadata-Version: 2.4
Name: stream-chat
Version: 4.29.0
Summary: Client for Stream Chat.
Home-page: https://github.com/GetStream/stream-chat-python
Author: Tommaso Barbugli
Author-email: support@getstream.io
Project-URL: Bug Tracker, https://github.com/GetStream/stream-chat-python/issues
Project-URL: Documentation, https://getstream.io/activity-feeds/docs/python/?language=python
Project-URL: Release Notes, https://github.com/GetStream/stream-chat-python/releases/tag/v4.29.0
Classifier: Intended Audience :: Developers
Classifier: Intended Audience :: System Administrators
Classifier: Operating System :: OS Independent
Classifier: Topic :: Software Development
Classifier: Development Status :: 5 - Production/Stable
Classifier: Natural Language :: English
Classifier: Programming Language :: Python :: 3
Classifier: Programming Language :: Python :: 3.8
Classifier: Programming Language :: Python :: 3.9
Classifier: Programming Language :: Python :: 3.10
Classifier: Programming Language :: Python :: 3.11
Classifier: Programming Language :: Python :: 3.12
Classifier: Topic :: Software Development :: Libraries :: Python Modules
Requires-Python: >=3.8
License-File: LICENSE
Requires-Dist: requests<3,>=2.22.0
Requires-Dist: aiodns>=2.0.0
Requires-Dist: aiohttp<4,>=3.6.0
Requires-Dist: aiofile<4,>=3.1
Requires-Dist: pyjwt<3,>=2.0.0
Requires-Dist: typing_extensions; python_version < "3.8"
Provides-Extra: test
Requires-Dist: pytest==8.1.1; extra == "test"
Requires-Dist: pytest-asyncio<=0.21.1; extra == "test"
Provides-Extra: ci
Requires-Dist: black; extra == "ci"
Requires-Dist: flake8; extra == "ci"
Requires-Dist: flake8-isort; extra == "ci"
Requires-Dist: flake8-bugbear; extra == "ci"
Requires-Dist: pytest-cov; extra == "ci"
Requires-Dist: mypy; extra == "ci"
Requires-Dist: types-requests; extra == "ci"
Dynamic: author
Dynamic: author-email
Dynamic: classifier
Dynamic: description
Dynamic: description-content-type
Dynamic: home-page
Dynamic: license-file
Dynamic: project-url
Dynamic: provides-extra
Dynamic: requires-dist
Dynamic: requires-python
Dynamic: summary
